setup.py
testcase_10/__init__.py
testcase_10/say_hello.py
testcase_10.egg-info/PKG-INFO
testcase_10.egg-info/SOURCES.txt
testcase_10.egg-info/dependency_links.txt
testcase_10.egg-info/top_level.txt