Metadata-Version: 2.1
Name: testcase-10
Version: 0.0.1
Summary: testcase_10
Author: Huading Su
Author-email: shd_596@163.com
License: Attribution-NonCommercial-ShareAlike 4.0
Requires-Python: >=3.10
